extralo/__init__.py
extralo/destination.py
extralo/etl.py
extralo/py.typed
extralo/source.py
extralo/destinations/__init__.py
extralo/destinations/delta_lake.py
extralo/destinations/file.py
extralo/destinations/sql.py
extralo/sources/__init__.py
extralo/sources/delta_lake.py
extralo/sources/file.py
extralo/sources/sql.py
extralo-2.0.1.dist-info/METADATA
extralo-2.0.1.dist-info/WHEEL
extralo-2.0.1.dist-info/RECORD
