Metadata-Version: 2.4
Name: extralo
Version: 2.0.1
Summary: ETL for Python
Author-email: Vitor Capdeville <vgcapdeville@hotmail.com>
Maintainer-email: Vitor Capdeville <vgcapdeville@hotmail.com>
Keywords: data,data-engineering,etl
Requires-Python: >=3.9
Requires-Dist: loguru
Provides-Extra: all
Requires-Dist: delta-spark; extra == 'all'
Requires-Dist: deltalake; extra == 'all'
Requires-Dist: openpyxl; extra == 'all'
Requires-Dist: pandas; extra == 'all'
Requires-Dist: pandas-stubs; extra == 'all'
Requires-Dist: pyspark; extra == 'all'
Requires-Dist: sqlalchemy; extra == 'all'
Requires-Dist: sqlparse; extra == 'all'
Provides-Extra: deltalake
Requires-Dist: deltalake; extra == 'deltalake'
Provides-Extra: pandas
Requires-Dist: openpyxl; extra == 'pandas'
Requires-Dist: pandas; extra == 'pandas'
Requires-Dist: pandas-stubs; extra == 'pandas'
Provides-Extra: spark
Requires-Dist: delta-spark; extra == 'spark'
Requires-Dist: pyspark; extra == 'spark'
Provides-Extra: sql
Requires-Dist: sqlalchemy; extra == 'sql'
Requires-Dist: sqlparse; extra == 'sql'
